xkcd_pass/__init__.py
xkcd_pass/xkcd_pass.py
xkcd_pass/lib/__init__.py
xkcd_pass/lib/case.py
xkcd_pass/static/.gitignore
xkcd_pass/static/eff-long
xkcd_pass/static/eff-short
xkcd_pass/static/eff-special
xkcd_pass/static/test_list
xkcd_pass/static/test_files/stdin_main_interactive
xkcd_pass-1.1.3.dist-info/LICENSE
xkcd_pass-1.1.3.dist-info/LICENSE.BSD
xkcd_pass-1.1.3.dist-info/METADATA
xkcd_pass-1.1.3.dist-info/WHEEL
xkcd_pass-1.1.3.dist-info/entry_points.txt
xkcd_pass-1.1.3.dist-info/top_level.txt
xkcd_pass-1.1.3.dist-info/RECORD
