Metadata-Version: 2.1
Name: xkcd-pass
Version: 1.1.3
Summary: Generate secure multiword passwords/passphrases, inspired by XKCD
Home-page: https://github.com/adambirds/xkcd-pass-python
Author: Adam Birds
Author-email: adam.birds@adbwebdesigns.co.uk
License: LGPLv3
Project-URL: Bug Tracker, https://github.com/adambirds/xkcd-pass-python/issues
Classifier: License :: OSI Approved :: GNU General Public License v3 (GPLv3)
Classifier: Programming Language :: Python
Classifier: Programming Language :: Python :: 3
Classifier: Programming Language :: Python :: 3.6
Classifier: Programming Language :: Python :: 3.7
Classifier: Programming Language :: Python :: 3.8
Classifier: Programming Language :: Python :: 3.9
Classifier: Programming Language :: Python :: 3.10
Classifier: Operating System :: OS Independent
Requires-Python: >=3.6
License-File: LICENSE
License-File: LICENSE.BSD
Requires-Dist: argcomplete
